LICENSE
README.md
setup.py
vyirc.py
vyirc.egg-info/PKG-INFO
vyirc.egg-info/SOURCES.txt
vyirc.egg-info/dependency_links.txt
vyirc.egg-info/top_level.txt